gloomhavenhelper/__init__.py
gloomhavenhelper/__main__.py
gloomhavenhelper/_ghh.so
gloomhavenhelper/ghh.py
gloomhavenhelper/protocol/__init__.py
gloomhavenhelper/protocol/_v7_6.so
gloomhavenhelper/protocol/_v8_0.so
gloomhavenhelper/protocol/_v8_4.so
gloomhavenhelper/protocol/v7_6.py
gloomhavenhelper/protocol/v8_0.py
gloomhavenhelper/protocol/v8_4.py
gloomhavenhelper-0.1.3.dist-info/METADATA
gloomhavenhelper-0.1.3.dist-info/WHEEL
gloomhavenhelper-0.1.3.dist-info/top_level.txt
gloomhavenhelper-0.1.3.dist-info/RECORD
