Metadata-Version: 2.1
Name: gloomhavenhelper
Version: 0.1.3
Summary: A server and client implementation to talk to GloomhavenHelper Application
Home-page: https://github.com/Gronis/gloomhaven-helper-rfid
Author: Gronis
Author-email: robingronberg@gmail.com
License: MIT
Platform: UNKNOWN
Classifier: License :: OSI Approved :: MIT License
Classifier: Programming Language :: Python :: 3
Classifier: Programming Language :: Python :: 3.7
